[
{"description": "Where programmers share ideas and help each other grow", "language": "Ruby", "repo": "dev.to", "new_stars": 1017, "stars": 4444, "owner": "thepracticaldev", "forks": 224},
{"description": "Bash Infinity is a modern boilerplate / framework / standard library for bash", "language": "Shell", "repo": "bash-oo-framework", "new_stars": 865, "stars": 2573, "owner": "niieani", "forks": 105},
{"description": "The Julia Language: A fresh approach to technical computing.", "language": "Julia", "repo": "julia", "new_stars": 652, "stars": 12518, "owner": "JuliaLang", "forks": 2494},
{"description": "Hardware backdoors in x86 CPUs", "language": "C", "repo": "rosenbridge", "new_stars": 548, "stars": 572, "owner": "xoreaxeaxeax", "forks": 52},
{"description": "A collection of pure bash alternatives to external processes.", "language": "Shell", "repo": "pure-bash-bible", "new_stars": 522, "stars": 8744, "owner": "dylanaraps", "forks": 438},
{"description": "A Social Media Enumeration & Correlation Tool by Jacob Wilkin(Greenwolf)", "language": "Python", "repo": "social_mapper", "new_stars": 435, "stars": 613, "owner": "SpiderLabs", "forks": 155},
{"description": "GitHub Load Balancer Director and supporting tooling.", "language": "C", "repo": "glb-director", "new_stars": 424, "stars": 987, "owner": "github", "forks": 69},
{"description": "A library for visualization and creative-coding", "language": "TypeScript", "repo": "pts", "new_stars": 415, "stars": 1886, "owner": "williamngan", "forks": 55},
{"description": "simple terminal UI for git commands", "language": "Go", "repo": "lazygit", "new_stars": 394, "stars": 6604, "owner": "jesseduffield", "forks": 161},
{"description": "A better and pretty variable inspector for your Node.js applications", "language": "JavaScript", "repo": "dumper.js", "new_stars": 347, "stars": 568, "owner": "zeeshanu", "forks": 13},
{"description": "100 Days of ML Coding", "language": null, "repo": "100-Days-Of-ML-Code", "new_stars": 311, "stars": 6484, "owner": "Avik-Jain", "forks": 1008},
{"description": "Learn Swift interactively on your iPhone.", "language": "Swift", "repo": "Unwrap", "new_stars": 255, "stars": 260, "owner": "twostraws", "forks": 16},
{"description": "Ever had a cool idea to an Open Source project but didn't have the time to implement yourself? Let someone else give it a try!", "language": null, "repo": "open-source-ideas", "new_stars": 254, "stars": 2584, "owner": "open-source-ideas", "forks": 55},
{"description": "Algorithms and data structures implemented in JavaScript with explanations and links to further readings", "language": "JavaScript", "repo": "javascript-algorithms", "new_stars": 232, "stars": 33319, "owner": "trekhleb", "forks": 3883},
{"description": "\u300aGo\u8bed\u8a00\u9ad8\u7ea7\u7f16\u7a0b\u300b\u5f00\u6e90\u56fe\u4e66\uff0c\u6db5\u76d6CGO\u3001Go\u6c47\u7f16\u8bed\u8a00\u3001RPC\u5b9e\u73b0\u3001Protobuf\u63d2\u4ef6\u5b9e\u73b0\u3001Web\u6846\u67b6\u5b9e\u73b0\u3001\u5206\u5e03\u5f0f\u7cfb\u7edf\u7b49\u9ad8\u9636\u4e3b\u9898", "language": "Go", "repo": "advanced-go-programming-book", "new_stars": 240, "stars": 4119, "owner": "chai2010", "forks": 404},
{"description": "Learn how to design large-scale systems. Prep for the system design interview. Includes Anki flashcards.", "language": "Python", "repo": "system-design-primer", "new_stars": 228, "stars": 40683, "owner": "donnemartin", "forks": 5229},
{"description": "React components for efficiently rendering large lists and tabular data", "language": "JavaScript", "repo": "react-window", "new_stars": 234, "stars": 1406, "owner": "bvaughn", "forks": 48},
{"description": "\u7a0b\u5e8f\u5458\u627e\u5de5\u4f5c\u9ed1\u540d\u5355\uff0c\u6362\u5de5\u4f5c\u548c\u5f53\u6280\u672f\u5408\u4f19\u4eba\u9700\u8c28\u614e\u554a", "language": null, "repo": "programmer-job-blacklist", "new_stars": 222, "stars": 8521, "owner": "shengxinjing", "forks": 631},
{"description": "Simplified HTTP requests", "language": "JavaScript", "repo": "got", "new_stars": 219, "stars": 3264, "owner": "sindresorhus", "forks": 192},
{"description": "Official Go implementation of the Vite protocol", "language": "Go", "repo": "go-vite", "new_stars": 183, "stars": 221, "owner": "vitelabs", "forks": 16},
{"description": "The best CLI client for Slack, because everything is terrible!", "language": "Python", "repo": "sclack", "new_stars": 169, "stars": 1134, "owner": "haskellcamargo", "forks": 29},
{"description": "A progressive, incrementally-adoptable JavaScript framework for building UI on the web.", "language": "JavaScript", "repo": "vue", "new_stars": 155, "stars": 110492, "owner": "vuejs", "forks": 15439},
{"description": "Darwin/macOS emulation layer for Linux", "language": "C", "repo": "darling", "new_stars": 166, "stars": 2426, "owner": "darlinghq", "forks": 130},
{"description": "curl for GraphQL with autocomplete, subscriptions and GraphiQL. Also a JS library", "language": "JavaScript", "repo": "graphqurl", "new_stars": 164, "stars": 283, "owner": "hasura", "forks": 6},
{"description": "\u9010\u884c\u7ea7\u522b\u7684\u6e90\u7801\u5206\u6790", "language": "JavaScript", "repo": "vue-design", "new_stars": 160, "stars": 2481, "owner": "HcySunYang", "forks": 226}
]