[
{"description": "Demonstrate all the questions on LeetCode in the form of animation.\uff08\u7528\u52a8\u753b\u7684\u5f62\u5f0f\u5448\u73b0\u89e3LeetCode\u9898\u76ee\u7684\u601d\u8def\uff09", "language": "C++", "repo": "LeetCodeAnimation", "new_stars": 5964, "stars": 10710, "owner": "MisterBooo", "forks": 1159},
{"description": "An Open Source Machine Learning Framework for Everyone", "language": "C++", "repo": "tensorflow", "new_stars": 2343, "stars": 118763, "owner": "tensorflow", "forks": 71400},
{"description": "An industrial deep learning framework for high-dimension sparse data", "language": "C++", "repo": "x-deeplearning", "new_stars": 1997, "stars": 2003, "owner": "alibaba", "forks": 421},
{"description": "Facebook AI Research Automatic Speech Recognition Toolkit", "language": "C++", "repo": "wav2letter", "new_stars": 1496, "stars": 3241, "owner": "facebookresearch", "forks": 452},
{"description": "Build cross-platform desktop apps with JavaScript, HTML, and CSS", "language": "C++", "repo": "electron", "new_stars": 1476, "stars": 68993, "owner": "electron", "forks": 8958},
{"description": "Tensors and Dynamic neural networks in Python with strong GPU acceleration", "language": "C++", "repo": "pytorch", "new_stars": 1211, "stars": 23921, "owner": "pytorch", "forks": 5676},
{"description": "Open Source Computer Vision Library", "language": "C++", "repo": "opencv", "new_stars": 891, "stars": 31125, "owner": "opencv", "forks": 22221},
{"description": "A Fractal Physics Game", "language": "C++", "repo": "MarbleMarcher", "new_stars": 1182, "stars": 1184, "owner": "HackerPoet", "forks": 67},
{"description": "Real-time Monitoring and Analysis of Data Streams", "language": "C++", "repo": "confluo", "new_stars": 904, "stars": 1201, "owner": "ucbrise", "forks": 170},
{"description": "Desktop implementations of the Flutter embedding API", "language": "C++", "repo": "flutter-desktop-embedding", "new_stars": 905, "stars": 3356, "owner": "google", "forks": 182},
{"description": "Protocol Buffers - Google's data interchange format", "language": "C++", "repo": "protobuf", "new_stars": 779, "stars": 31588, "owner": "protocolbuffers", "forks": 8677},
{"description": "Godot Engine \u2013 Multi-platform 2D and 3D game engine", "language": "C++", "repo": "godot", "new_stars": 711, "stars": 18887, "owner": "godotengine", "forks": 3803},
{"description": "Tesseract Open Source OCR Engine (main repository)", "language": "C++", "repo": "tesseract", "new_stars": 695, "stars": 23748, "owner": "tesseract-ocr", "forks": 4647},
{"description": "A C++ standalone library for machine learning", "language": "C++", "repo": "flashlight", "new_stars": 708, "stars": 708, "owner": "facebookresearch", "forks": 61},
{"description": "Bitcoin Core integration/staging tree", "language": "C++", "repo": "bitcoin", "new_stars": 530, "stars": 36799, "owner": "bitcoin", "forks": 21905},
{"description": "The C based gRPC (C++, Python, Ruby, Objective-C, PHP, C#)", "language": "C++", "repo": "grpc", "new_stars": 552, "stars": 19049, "owner": "grpc", "forks": 4388},
{"description": "NVIDIA PhysX SDK", "language": "C++", "repo": "PhysX", "new_stars": 523, "stars": 523, "owner": "NVIDIAGameWorks", "forks": 71},
{"description": "Provide ESP8266 based itead Sonoff with Web, MQTT and OTA firmware using Arduino IDE or PlatformIO", "language": "C++", "repo": "Sonoff-Tasmota", "new_stars": 494, "stars": 5500, "owner": "arendst", "forks": 1262},
{"description": "An open autonomous driving platform", "language": "C++", "repo": "apollo", "new_stars": 438, "stars": 12238, "owner": "ApolloAuto", "forks": 3631},
{"description": "OpenPose: Real-time multi-person keypoint detection library for body, face, hands, and foot estimation", "language": "C++", "repo": "openpose", "new_stars": 475, "stars": 10767, "owner": "CMU-Perceptual-Computing-Lab", "forks": 2935},
{"description": "Dear ImGui: Bloat-free Immediate Mode Graphical User interface for C++ with minimal dependencies", "language": "C++", "repo": "imgui", "new_stars": 470, "stars": 13342, "owner": "ocornut", "forks": 1837},
{"description": "Cloud-native high-performance edge/middle/service proxy", "language": "C++", "repo": "envoy", "new_stars": 461, "stars": 8049, "owner": "envoyproxy", "forks": 1160},
{"description": "Cross-platform GUI management tool for Redis", "language": "C++", "repo": "RedisDesktopManager", "new_stars": 428, "stars": 10753, "owner": "uglide", "forks": 1686},
{"description": "JSON for Modern C++", "language": "C++", "repo": "json", "new_stars": 435, "stars": 12521, "owner": "nlohmann", "forks": 2018},
{"description": "Cryptocurrency for world adoption.", "language": "C++", "repo": "energi", "new_stars": 467, "stars": 1276, "owner": "energicryptocurrency", "forks": 21905}
]