[
{"description": "Walt is a JavaScript-like syntax for WebAssembly text format", "language": "JavaScript", "repo": "walt", "new_stars": 797, "stars": 3096, "owner": "ballercat", "forks": 99},
{"description": "A curated list of delightful VS Code packages and resources.", "language": "JavaScript", "repo": "awesome-vscode", "new_stars": 285, "stars": 10488, "owner": "viatsko", "forks": 507},
{"description": "Composable data visualisation library for web with a data-first approach", "language": "JavaScript", "repo": "muze", "new_stars": 257, "stars": 304, "owner": "chartshq", "forks": 6},
{"description": "Curated collection of useful JavaScript snippets that you can understand in 30 seconds or less.", "language": "JavaScript", "repo": "30-seconds-of-code", "new_stars": 244, "stars": 28048, "owner": "30-seconds", "forks": 2837},
{"description": "Starter Files and Solutions for Full Stack Advanced React and GraphQL", "language": "JavaScript", "repo": "Advanced-React", "new_stars": 143, "stars": 420, "owner": "wesbos", "forks": 130},
{"description": "A rich-text editor for Vue.js", "language": "JavaScript", "repo": "tiptap", "new_stars": 137, "stars": 1445, "owner": "heyscrumpy", "forks": 50},
{"description": "A very fast static spatial index for 2D points and rectangles in JavaScript", "language": "JavaScript", "repo": "flatbush", "new_stars": 123, "stars": 665, "owner": "mourner", "forks": 24},
{"description": "Simple React Native testing utilities helping you write better tests with less effort", "language": "JavaScript", "repo": "react-native-testing-library", "new_stars": 121, "stars": 150, "owner": "callstack", "forks": 3},
{"description": "A progressive, incrementally-adoptable JavaScript framework for building UI on the web.", "language": "JavaScript", "repo": "vue", "new_stars": 101, "stars": 116193, "owner": "vuejs", "forks": 16390},
{"description": "Re-usable, easy interface JavaScript chart library based on D3 v4+", "language": "JavaScript", "repo": "billboard.js", "new_stars": 106, "stars": 3073, "owner": "naver", "forks": 174},
{"description": "A declarative, efficient, and flexible JavaScript library for building user interfaces.", "language": "JavaScript", "repo": "react", "new_stars": 78, "stars": 112931, "owner": "facebook", "forks": 20260},
{"description": "Create React apps with no build configuration.", "language": "JavaScript", "repo": "create-react-app", "new_stars": 71, "stars": 57262, "owner": "facebook", "forks": 12247},
{"description": "Node.js JavaScript runtime", "language": "JavaScript", "repo": "node", "new_stars": 45, "stars": 54254, "owner": "nodejs", "forks": 11630},
{"description": "JavaScript Style Guide", "language": "JavaScript", "repo": "javascript", "new_stars": 60, "stars": 76944, "owner": "airbnb", "forks": 14705},
{"description": "Headless Chrome Node API", "language": "JavaScript", "repo": "puppeteer", "new_stars": 63, "stars": 39412, "owner": "GoogleChrome", "forks": 3299},
{"description": "A simple Electron Wrapper that converts Google Drive into a desktop office suite app.", "language": "JavaScript", "repo": "Google-Drive-Electron", "new_stars": 66, "stars": 93, "owner": "alexkim205", "forks": 4},
{"description": "A framework for building native apps with React.", "language": "JavaScript", "repo": "react-native", "new_stars": 55, "stars": 69668, "owner": "facebook", "forks": 15631},
{"description": "\uf8ff Now we have become very big, Different from the original idea. Collect premium software in various categories.", "language": "JavaScript", "repo": "awesome-mac", "new_stars": 55, "stars": 21652, "owner": "jaywcjlove", "forks": 2604},
{"description": "The React Framework", "language": "JavaScript", "repo": "next.js", "new_stars": 49, "stars": 30247, "owner": "zeit", "forks": 3123},
{"description": "Algorithms and data structures implemented in JavaScript with explanations and links to further readings", "language": "JavaScript", "repo": "javascript-algorithms", "new_stars": 47, "stars": 37941, "owner": "trekhleb", "forks": 4746},
{"description": "\u5fae\u4fe1\u5c0f\u7a0b\u5e8f\u5f00\u53d1\u8d44\u6e90\u6c47\u603b", "language": "JavaScript", "repo": "awesome-wechat-weapp", "new_stars": 45, "stars": 18291, "owner": "justjavac", "forks": 3926},
{"description": "Build blazing fast, modern apps and websites with React", "language": "JavaScript", "repo": "gatsby", "new_stars": 42, "stars": 26615, "owner": "gatsbyjs", "forks": 3129},
{"description": "State so simple, it goes without saying", "language": "JavaScript", "repo": "unstated", "new_stars": 43, "stars": 4538, "owner": "jamiebuilds", "forks": 142},
{"description": "Object oriented state management solution for front-end development.", "language": "JavaScript", "repo": "Radon", "new_stars": 43, "stars": 50, "owner": "radonjs", "forks": 5},
{"description": "A modern JavaScript utility library delivering modularity, performance, & extras.", "language": "JavaScript", "repo": "lodash", "new_stars": 40, "stars": 35097, "owner": "lodash", "forks": 3644}
]