[
{"description": "Powerful yet simple to use screenshot software", "language": "C++", "repo": "flameshot", "new_stars": 317, "stars": 16231, "owner": "flameshot-org", "forks": 1017},
{"description": "Nintendo Switch Emulator", "language": "C++", "repo": "yuzu", "new_stars": 269, "stars": 18476, "owner": "yuzu-emu", "forks": 1560},
{"description": "The Magic Mask for Android", "language": "C++", "repo": "Magisk", "new_stars": 475, "stars": 23329, "owner": "topjohnwu", "forks": 5536},
{"description": "Build cross-platform desktop apps with JavaScript, HTML, and CSS", "language": "C++", "repo": "electron", "new_stars": 176, "stars": 100069, "owner": "electron", "forks": 13151},
{"description": "Tensors and Dynamic neural networks in Python with strong GPU acceleration", "language": "C++", "repo": "pytorch", "new_stars": 196, "stars": 53750, "owner": "pytorch", "forks": 14842},
{"description": "A monitor of resources", "language": "C++", "repo": "btop", "new_stars": 81, "stars": 6085, "owner": "aristocratos", "forks": 208},
{"description": "The C based gRPC (C++, Python, Ruby, Objective-C, PHP, C#)", "language": "C++", "repo": "grpc", "new_stars": 71, "stars": 33232, "owner": "grpc", "forks": 8722},
{"description": "Collection of various algorithms in mathematics, machine learning, computer science and physics implemented in C++ for educational purposes.", "language": "C++", "repo": "C-Plus-Plus", "new_stars": 119, "stars": 17763, "owner": "TheAlgorithms", "forks": 4861},
{"description": "Notepad++ official repository", "language": "C++", "repo": "notepad-plus-plus", "new_stars": 67, "stars": 15072, "owner": "notepad-plus-plus", "forks": 3449},
{"description": "Open 3D Engine (O3DE) is an Apache 2.0-licensed multi-platform 3D engine that enables developers and content creators to build AAA games, cinema-quality 3D worlds, and high-fidelity simulations without any fees or commercial obligations.", "language": "C++", "repo": "o3de", "new_stars": 36, "stars": 4321, "owner": "o3de", "forks": 1329},
{"description": "Windscribe 2.0 desktop client for Windows, Mac and Linux", "language": "C++", "repo": "desktop-v2", "new_stars": 27, "stars": 166, "owner": "Windscribe", "forks": 20},
{"description": "Dear ImGui: Bloat-free Graphical User interface for C++ with minimal dependencies", "language": "C++", "repo": "imgui", "new_stars": 115, "stars": 34394, "owner": "ocornut", "forks": 5938},
{"description": "\u660e\u65e5\u65b9\u821f\u52a9\u624b\uff0c\u81ea\u52a8\u5237\u56fe\u3001\u667a\u80fd\u57fa\u5efa\u6362\u73ed\uff0c\u5168\u65e5\u5e38\u4e00\u952e\u957f\u8349\uff01", "language": "C++", "repo": "MeoAssistantArknights", "new_stars": 155, "stars": 589, "owner": "MistEO", "forks": 59},
{"description": "Redpanda is the real-time engine for modern apps. Kafka API Compatible; 10x faster", "language": "C++", "repo": "redpanda", "new_stars": 50, "stars": 3314, "owner": "vectorizedio", "forks": 204},
{"description": "Cloud-native high-performance edge/middle/service proxy", "language": "C++", "repo": "envoy", "new_stars": 52, "stars": 18854, "owner": "envoyproxy", "forks": 3514},
{"description": "Google SafetyNet attestation workarounds for Magisk", "language": "C++", "repo": "safetynet-fix", "new_stars": 299, "stars": 2314, "owner": "kdrag0n", "forks": 134},
{"description": "Translation of", "language": "C++", "repo": "e-maxx-eng", "new_stars": 57, "stars": 1813, "owner": "e-maxx-eng", "forks": 535},
{"description": "BladeDISC is an end-to-end DynamIc Shape Compiler project for machine learning workloads.", "language": "C++", "repo": "BladeDISC", "new_stars": 62, "stars": 194, "owner": "alibaba", "forks": 41},
{"description": "Apache Arrow is a multi-language toolbox for accelerated data interchange and in-memory processing", "language": "C++", "repo": "arrow", "new_stars": 38, "stars": 9023, "owner": "apache", "forks": 2195},
{"description": "Intel\u00ae RealSense\u2122 SDK", "language": "C++", "repo": "librealsense", "new_stars": 16, "stars": 5724, "owner": "IntelRealSense", "forks": 4083},
{"description": "Productive & portable high-performance programming in Python.", "language": "C++", "repo": "taichi", "new_stars": 67, "stars": 17958, "owner": "taichi-dev", "forks": 1849},
{"description": "OpenVINO\u2122 Toolkit repository", "language": "C++", "repo": "openvino", "new_stars": 26, "stars": 2978, "owner": "openvinotoolkit", "forks": 1274},
{"description": "Atmosph\u00e8re is a work-in-progress customized firmware for the Nintendo Switch.", "language": "C++", "repo": "Atmosphere", "new_stars": 47, "stars": 8330, "owner": "Atmosphere-NX", "forks": 814},
{"description": "A fast multi-producer, multi-consumer lock-free concurrent queue for C++11", "language": "C++", "repo": "concurrentqueue", "new_stars": 22, "stars": 6410, "owner": "cameron314", "forks": 1298},
{"description": "FoundationDB - the open source, distributed, transactional key-value store", "language": "C++", "repo": "foundationdb", "new_stars": 11, "stars": 11014, "owner": "apple", "forks": 1038}
]