[
{"description": "Repo for counting stars and contributing. Press F to pay respect to glorious developers.", "language": "Rust", "repo": "996.ICU", "new_stars": 8457, "stars": 195238, "owner": "996icu", "forks": 15538},
{"description": "\u300a\u795e\u7ecf\u7f51\u7edc\u4e0e\u6df1\u5ea6\u5b66\u4e60\u300b Neural Network and Deep Learning", "language": "HTML", "repo": "nndl.github.io", "new_stars": 1463, "stars": 4057, "owner": "nndl", "forks": 873},
{"description": "A strong, neutral, principles-driven, open-source typeface for text or display", "language": "HTML", "repo": "public-sans", "new_stars": 773, "stars": 913, "owner": "uswds", "forks": 22},
{"description": "Your new Mentor for Data Science E-Learning.", "language": "Jupyter Notebook", "repo": "Virgilio", "new_stars": 647, "stars": 8139, "owner": "clone95", "forks": 1503},
{"description": "955 \u4e0d\u52a0\u73ed\u7684\u516c\u53f8\u540d\u5355", "language": null, "repo": "955.WLB", "new_stars": 700, "stars": 12715, "owner": "formulahendry", "forks": 485},
{"description": "A just-add-css collection of styles to make simple websites just a little nicer", "language": "HTML", "repo": "water.css", "new_stars": 695, "stars": 2142, "owner": "kognise", "forks": 59},
{"description": "A Collection of application ideas which can be used to improve your coding skills.", "language": null, "repo": "app-ideas", "new_stars": 652, "stars": 1893, "owner": "florinpop17", "forks": 124},
{"description": "The OWASP Cheat Sheet Series was created to provide a concise collection of high value information on specific application security topics.", "language": "Python", "repo": "CheatSheetSeries", "new_stars": 566, "stars": 3399, "owner": "OWASP", "forks": 437},
{"description": "\u5faa\u5e8f\u6e10\u8fdb\uff0c\u5b66\u4e60Spring Boot\u3001Spring Boot & Shiro\u3001Spring Cloud\u548cSpring Security\uff0c\u535a\u5ba2Spring\u7cfb\u5217\u6e90\u7801", "language": "Java", "repo": "SpringAll", "new_stars": 553, "stars": 2924, "owner": "wuyouzhuguli", "forks": 572},
{"description": "The best design tools for everything", "language": "JavaScript", "repo": "Awesome-Design-Tools", "new_stars": 454, "stars": 12480, "owner": "LisaDziuba", "forks": 690},
{"description": "\u7a0b\u5e8f\u5458\u627e\u5de5\u4f5c\u9ed1\u540d\u5355\uff0c\u6362\u5de5\u4f5c\u548c\u5f53\u6280\u672f\u5408\u4f19\u4eba\u9700\u8c28\u614e\u554a \u66f4\u65b0\u6709\u8d5e", "language": "Shell", "repo": "programmer-job-blacklist", "new_stars": 450, "stars": 21309, "owner": "shengxinjing", "forks": 1346},
{"description": "A block-styled editor with clean JSON output", "language": "TypeScript", "repo": "editor.js", "new_stars": 437, "stars": 4962, "owner": "codex-team", "forks": 161},
{"description": "\u300a\u673a\u5668\u5b66\u4e60\u300b\uff08\u897f\u74dc\u4e66\uff09\u516c\u5f0f\u63a8\u5bfc\u89e3\u6790\uff0c\u5728\u7ebf\u9605\u8bfb\u5730\u5740\uff1a", "language": null, "repo": "pumpkin-book", "new_stars": 406, "stars": 3777, "owner": "datawhalechina", "forks": 626},
{"description": "Complete Mandiant Offensive VM (Commando VM), the first full Windows-based penetration testing virtual machine distribution. The security community recognizes Kali Linux as the go-to penetration testing platform for those that prefer Linux. Commando VM is for penetration testers that prefer Windows. We know that building a Windows penetration te\u2026", "language": "PowerShell", "repo": "commando-vm", "new_stars": 344, "stars": 1633, "owner": "fireeye", "forks": 325},
{"description": "\u5317\u4eac\u5927\u5b66\u8bfe\u7a0b\u8d44\u6599\u6574\u7406", "language": "JavaScript", "repo": "libpku", "new_stars": 353, "stars": 3212, "owner": "lib-pku", "forks": 1084},
{"description": "A work-in-progress, open-source, multi-player city simulation game.", "language": "Rust", "repo": "citybound", "new_stars": 373, "stars": 4513, "owner": "citybound", "forks": 138},
{"description": "Default configuration for Le Wagon's students", "language": "Shell", "repo": "dotfiles", "new_stars": 250, "stars": 4572, "owner": "lewagon", "forks": 5055},
{"description": "Examples of how to do query, style, dom, ajax, event etc like jQuery with plain javascript.", "language": "JavaScript", "repo": "You-Dont-Need-jQuery", "new_stars": 340, "stars": 17334, "owner": "nefe", "forks": 1536},
{"description": "996ICU 995ICU \u5de5\u4f5c996 \u751f\u75c5ICU \u52a0\u73ed\u4e0d\u89c4\u8303 \u4eb2\u4eba\u4e24\u884c\u6cea", "language": null, "repo": "996ICU", "new_stars": 276, "stars": 2538, "owner": "995icu", "forks": 149},
{"description": "HACL*, a formally verified cryptographic library written in F*", "language": "Assembly", "repo": "hacl-star", "new_stars": 273, "stars": 942, "owner": "project-everest", "forks": 68},
{"description": "Extensions giving Swift's Codable API type inference super powers \ud83e\uddb8\u200d\u2642\ufe0f\ud83e\uddb9\u200d\u2640\ufe0f", "language": "Swift", "repo": "Codextended", "new_stars": 277, "stars": 291, "owner": "JohnSundell", "forks": 7},
{"description": "\u9003\u79bb996", "language": null, "repo": "996.Leave", "new_stars": 273, "stars": 811, "owner": "623637646", "forks": 44},
{"description": "\u3010Java\u5b66\u4e60+\u9762\u8bd5\u6307\u5357\u3011 \u4e00\u4efd\u6db5\u76d6\u5927\u90e8\u5206Java\u7a0b\u5e8f\u5458\u6240\u9700\u8981\u638c\u63e1\u7684\u6838\u5fc3\u77e5\u8bc6\u3002", "language": "Java", "repo": "JavaGuide", "new_stars": 237, "stars": 34111, "owner": "Snailclimb", "forks": 10511},
{"description": "Modern low-level programming language", "language": "C", "repo": "muon", "new_stars": 250, "stars": 371, "owner": "nickmqb", "forks": 7},
{"description": null, "language": "JavaScript", "repo": "ElGrapho", "new_stars": 244, "stars": 522, "owner": "ericdrowell", "forks": 30}
]