[
{"description": "Create self-contained single binary applications", "language": "Rust", "repo": "warp", "new_stars": 779, "stars": 894, "owner": "dgiagio", "forks": 19},
{"description": "An efficient programming language and proof assistant.", "language": "Rust", "repo": "Formality", "new_stars": 378, "stars": 387, "owner": "MaiaVictor", "forks": 11},
{"description": "Minimal implementation of the MimbleWimble protocol.", "language": "Rust", "repo": "grin", "new_stars": 314, "stars": 2030, "owner": "mimblewimble", "forks": 327},
{"description": "A cat(1) clone with wings.", "language": "Rust", "repo": "bat", "new_stars": 166, "stars": 9172, "owner": "sharkdp", "forks": 161},
{"description": "A safe, concurrent, practical language.", "language": "Rust", "repo": "rust", "new_stars": 131, "stars": 31210, "owner": "rust-lang", "forks": 5240},
{"description": "A cross-platform, GPU-accelerated terminal emulator", "language": "Rust", "repo": "alacritty", "new_stars": 125, "stars": 12625, "owner": "jwilm", "forks": 545},
{"description": "A modern editor with a backend written in Rust.", "language": "Rust", "repo": "xi-editor", "new_stars": 108, "stars": 14954, "owner": "xi-editor", "forks": 542},
{"description": "Dynamically changing, partially-stateful data-flow for web application backends.", "language": "Rust", "repo": "noria", "new_stars": 91, "stars": 334, "owner": "mit-pdos", "forks": 15},
{"description": "Minimalist command line tool you can use to track and examine your habits.", "language": "Rust", "repo": "habitctl", "new_stars": 89, "stars": 96, "owner": "blinry", "forks": 5},
{"description": "Rust syntax sugar collections.", "language": "Rust", "repo": "sugar-rs", "new_stars": 88, "stars": 90, "owner": "harryfei", "forks": 1},
{"description": "research", "language": "Rust", "repo": "shifgrethor", "new_stars": 87, "stars": 97, "owner": "withoutboats", "forks": 1},
{"description": "A simple, fast and user-friendly alternative to 'find'", "language": "Rust", "repo": "fd", "new_stars": 68, "stars": 7041, "owner": "sharkdp", "forks": 180},
{"description": "Data-oriented, and data driven game engine written in Rust", "language": "Rust", "repo": "amethyst", "new_stars": 66, "stars": 1782, "owner": "amethyst", "forks": 198},
{"description": "Static analysis tools for all programming languages", "language": "Rust", "repo": "awesome-static-analysis", "new_stars": 59, "stars": 4021, "owner": "mre", "forks": 459},
{"description": "Actix web is a small, pragmatic, and extremely fast rust web framework.", "language": "Rust", "repo": "actix-web", "new_stars": 58, "stars": 2605, "owner": "actix", "forks": 171},
{"description": "Rust client for Kubernetes", "language": "Rust", "repo": "kubernetes-rust", "new_stars": 58, "stars": 59, "owner": "ynqa", "forks": 0},
{"description": "deserialize env vars into typesafe structs with rust", "language": "Rust", "repo": "envy", "new_stars": 56, "stars": 187, "owner": "softprops", "forks": 6},
{"description": "A bunch of lints to catch common mistakes and improve your Rust code", "language": "Rust", "repo": "rust-clippy", "new_stars": 54, "stars": 2561, "owner": "rust-lang-nursery", "forks": 362},
{"description": "A curated list of Rust code and resources.", "language": "Rust", "repo": "awesome-rust", "new_stars": 51, "stars": 8269, "owner": "rust-unofficial", "forks": 549},
{"description": "A web framework for Rust.", "language": "Rust", "repo": "Rocket", "new_stars": 49, "stars": 5395, "owner": "SergioBenitez", "forks": 347},
{"description": "An experimental next-generation Electron-based text editor", "language": "Rust", "repo": "xray", "new_stars": 49, "stars": 8123, "owner": "atom", "forks": 198},
{"description": "Replacement for 'ls' written in Rust.", "language": "Rust", "repo": "exa", "new_stars": 47, "stars": 4898, "owner": "ogham", "forks": 154},
{"description": "The Servo Browser Engine", "language": "Rust", "repo": "servo", "new_stars": 43, "stars": 12592, "owner": "servo", "forks": 1974},
{"description": "Bahasa pemrograman dengan sintaks Bahasa Indonesia (Programming language with Indonesian syntax)", "language": "Rust", "repo": "naskah", "new_stars": 47, "stars": 47, "owner": "pveyes", "forks": 3},
{"description": "A runtime for writing reliable, asynchronous, and slim applications with the Rust programming language.", "language": "Rust", "repo": "tokio", "new_stars": 42, "stars": 3358, "owner": "tokio-rs", "forks": 237}
]