[
{"description": "spring boot demo \u662f\u4e00\u4e2a\u7528\u6765\u5b66\u4e60 spring boot \u7684\u9879\u76ee\uff0c\u603b\u5171\u5305\u542b 57 \u4e2a\u96c6\u6210demo\uff0c\u5df2\u7ecf\u5b8c\u6210 47 \u4e2a\u3002\u5305\u542b\u96c6\u6210 actuator(\u76d1\u63a7)\u3001admin(\u53ef\u89c6\u5316\u76d1\u63a7)\u3001logback(\u65e5\u5fd7)\u3001aopLog(\u901a\u8fc7AOP\u8bb0\u5f55web\u8bf7\u6c42\u65e5\u5fd7)\u3001\u7edf\u4e00\u5f02\u5e38\u5904\u7406(json\u7ea7\u522b\u548c\u9875\u9762\u7ea7\u522b)\u3001freemarker(\u6a21\u677f\u5f15\u64ce)\u3001thymeleaf(\u6a21\u677f\u5f15\u64ce)\u3001Beetl(\u6a21\u677f\u5f15\u64ce)\u3001Enjoy(\u6a21\u677f\u5f15\u64ce)\u3001JdbcTemplate\u3001JPA(ORM\u6846\u67b6)\u3001mybatis(ORM\u6846\u67b6)\u3001\u901a\u7528Mapper\u3001PageHelper\u3001mybatis-plus\u3001BeetlSQL\u3001upload(\u672c\u5730\u6587\u4ef6\u4e0a\u4f20\u548c\u4e03\u725b\u4e91\u6587\u4ef6\u4e0a\u4f20)\u3001redis(\u7f13\u5b58)\u3001ehcache(\u7f13\u5b58)\u3001email(\u53d1\u9001\u5404\u79cd\u7c7b\u2026", "language": "Java", "repo": "spring-boot-demo", "new_stars": 1166, "stars": 2347, "owner": "xkcoding", "forks": 752},
{"description": "C-OCR\u662f\u643a\u7a0b\u81ea\u7814\u7684OCR\u9879\u76ee\uff0c\u4e3b\u8981\u5305\u62ec\u8eab\u4efd\u8bc1\u3001\u62a4\u7167\u3001\u706b\u8f66\u7968\u3001\u7b7e\u8bc1\u7b49\u65c5\u6e38\u76f8\u5173\u8bc1\u4ef6\u3001\u6750\u6599\u7684\u8bc6\u522b\u3002 \u9879\u76ee\u5305\u542b4\u4e2a\u90e8\u5206\uff0c\u62d2\u8bc6\u3001\u68c0\u6d4b\u3001\u8bc6\u522b\u3001\u540e\u5904\u7406\u3002", "language": "Java", "repo": "C-OCR", "new_stars": 884, "stars": 1205, "owner": "ctripcorp", "forks": 268},
{"description": "\u78c1\u529b\u641c\u7f51\u9875\u7248 - \u78c1\u529b\u94fe\u63a5\u805a\u5408\u641c\u7d22 -", "language": "Java", "repo": "magnetW", "new_stars": 674, "stars": 2440, "owner": "dengyuhan", "forks": 522},
{"description": "\u2b50\u2b50\u2b50\u2b50\u79d2\u6740\u7cfb\u7edf\u8bbe\u8ba1\u4e0e\u5b9e\u73b0.\u4e92\u8054\u7f51\u5de5\u7a0b\u5e08\u8fdb\u9636\u4e0e\u5206\u6790", "language": "Java", "repo": "miaosha", "new_stars": 673, "stars": 10434, "owner": "qiurunze123", "forks": 2212},
{"description": "To Be Top Javaer - Java\u5de5\u7a0b\u5e08\u6210\u795e\u4e4b\u8def", "language": "Java", "repo": "toBeTopJavaer", "new_stars": 876, "stars": 7269, "owner": "hollischuang", "forks": 1576},
{"description": "\u3010\u5495\u6ce1\u5b66\u9662\u5b9e\u6218\u9879\u76ee\u3011-\u57fa\u4e8eSpringBoot+Dubbo\u6784\u5efa\u7684\u7535\u5546\u5e73\u53f0-\u5fae\u670d\u52a1\u67b6\u6784\u3001\u5546\u57ce\u3001\u7535\u5546\u3001\u5fae\u670d\u52a1\u3001\u9ad8\u5e76\u53d1\u3001kafka", "language": "Java", "repo": "gpmall", "new_stars": 796, "stars": 1029, "owner": "2227324689", "forks": 380},
{"description": "fullstack tutorial 2019\uff0c\u540e\u53f0\u6280\u672f\u6808/\u67b6\u6784\u5e08\u4e4b\u8def/\u5168\u6808\u5f00\u53d1\u793e\u533a\uff0c\u6625\u62db/\u79cb\u62db/\u6821\u62db/\u9762\u8bd5", "language": "Java", "repo": "fullstack-tutorial", "new_stars": 705, "stars": 5215, "owner": "frank-lam", "forks": 1111},
{"description": "\u4e00\u6b3e\u73b0\u4ee3\u5316\u7684\u811a\u624b\u67b6\u9879\u76ee\u3002\u4f01\u4e1a\u5f00\u53d1\uff1f\u63a5\u5916\u5305\uff1f\u8d5a\u5916\u5feb\uff1f\u8fd8\u662f\u5b66\u4e60\uff1f\u8fd9\u90fd\u80fd\u6ee1\u8db3\u4f60\uff0c\u5c45\u5bb6\u5fc5\u5907\uff0c\u503c\u5f97\u62e5\u6709", "language": "Java", "repo": "hope-boot", "new_stars": 552, "stars": 1556, "owner": "hope-for", "forks": 310},
{"description": "APM, Application Performance Monitoring System", "language": "Java", "repo": "skywalking", "new_stars": 284, "stars": 9856, "owner": "apache", "forks": 2834},
{"description": "mall\u5b66\u4e60\u6559\u7a0b\uff0c\u67b6\u6784\u3001\u4e1a\u52a1\u3001\u6280\u672f\u8981\u70b9\u5168\u65b9\u4f4d\u89e3\u6790\u3002mall\u9879\u76ee\uff0818k+star\uff09\u662f\u4e00\u5957\u7535\u5546\u7cfb\u7edf\uff0c\u4f7f\u7528\u73b0\u9636\u6bb5\u4e3b\u6d41\u6280\u672f\u5b9e\u73b0\u3002 \u6db5\u76d6\u4e86SpringBoot2.1.3\u3001MyBatis3.4.6\u3001Elasticsearch6.2.2\u3001RabbitMQ3.7.15\u3001Redis3.2\u3001Mongodb3.2\u3001Mysql5.7\u7b49\u6280\u672f\uff0c\u91c7\u7528Docker\u5bb9\u5668\u5316\u90e8\u7f72\u3002", "language": "Java", "repo": "mall-learning", "new_stars": 196, "stars": 1764, "owner": "macrozheng", "forks": 734},
{"description": "\u57fa\u4e8eSpringCloud2.0\u7684\u5fae\u670d\u52a1\u5f00\u53d1\u811a\u624b\u67b6\uff0c\u6574\u5408\u4e86spring-security-oauth2\u3001apollo\u3001eureka\u3001feign\u3001hystrix\u3001springcloud-gateway\u3001springcloud-bus\u7b49\u3002\u6cbb\u7406\u65b9\u9762\u5f15\u5165elasticsearch\u3001skywalking\u3001springboot-admin\u3001zipkin\u7b49\uff0c\u8ba9\u9879\u76ee\u5f00\u53d1\u5feb\u901f\u8fdb\u5165\u4e1a\u52a1\u5f00\u53d1\uff0c\u800c\u4e0d\u9700\u8fc7\u591a\u65f6\u95f4\u82b1\u8d39\u5728\u67b6\u6784\u642d\u5efa\u4e0a\u3002\u6301\u7eed\u66f4\u65b0\u4e2d", "language": "Java", "repo": "SpringCloud", "new_stars": 118, "stars": 1052, "owner": "zhoutaoo", "forks": 587},
{"description": "Spring Cloud Alibaba provides a one-stop solution for application development for the distributed solutions of Alibaba middleware.", "language": "Java", "repo": "spring-cloud-alibaba", "new_stars": 249, "stars": 8137, "owner": "alibaba", "forks": 2224},
{"description": "Ghidra is a software reverse engineering (SRE) framework", "language": "Java", "repo": "ghidra", "new_stars": 152, "stars": 16995, "owner": "NationalSecurityAgency", "forks": 2144},
{"description": "Spring Boot", "language": "Java", "repo": "spring-boot", "new_stars": 224, "stars": 40986, "owner": "spring-projects", "forks": 26408},
{"description": null, "language": "Java", "repo": "DataX", "new_stars": 88, "stars": 3441, "owner": "alibaba", "forks": 1334},
{"description": "\u81ea\u7136\u8bed\u8a00\u5904\u7406 \u4e2d\u6587\u5206\u8bcd \u8bcd\u6027\u6807\u6ce8 \u547d\u540d\u5b9e\u4f53\u8bc6\u522b \u4f9d\u5b58\u53e5\u6cd5\u5206\u6790 \u65b0\u8bcd\u53d1\u73b0 \u5173\u952e\u8bcd\u77ed\u8bed\u63d0\u53d6 \u81ea\u52a8\u6458\u8981 \u6587\u672c\u5206\u7c7b\u805a\u7c7b \u62fc\u97f3\u7b80\u7e41", "language": "Java", "repo": "HanLP", "new_stars": 118, "stars": 14403, "owner": "hankcs", "forks": 4095},
{"description": "BRVAH:Powerful and flexible RecyclerAdapter", "language": "Java", "repo": "BaseRecyclerViewAdapterHelper", "new_stars": 81, "stars": 17971, "owner": "CymChad", "forks": 3769},
{"description": "Java Core Sprout : basic, concurrent, algorithm", "language": "Java", "repo": "JCSprout", "new_stars": 125, "stars": 22000, "owner": "crossoverJie", "forks": 6097},
{"description": "A lightweight distributed task scheduling framework.\uff08\u5206\u5e03\u5f0f\u4efb\u52a1\u8c03\u5ea6\u5e73\u53f0XXL-JOB\uff09", "language": "Java", "repo": "xxl-job", "new_stars": 128, "stars": 9550, "owner": "xuxueli", "forks": 4089},
{"description": "Distributed database middleware", "language": "Java", "repo": "incubator-shardingsphere", "new_stars": 81, "stars": 8496, "owner": "apache", "forks": 2947},
{"description": "\u7b80\u79f0 \"DoKit\" \u3002\u4e00\u6b3e\u529f\u80fd\u9f50\u5168\u7684\u5ba2\u6237\u7aef\uff08 iOS \u3001Android \uff09\u7814\u53d1\u52a9\u624b\uff0c\u4f60\u503c\u5f97\u62e5\u6709\u3002", "language": "Java", "repo": "DoraemonKit", "new_stars": 153, "stars": 9514, "owner": "didi", "forks": 1186},
{"description": "\u9605\u8bfb\u662f\u4e00\u6b3e\u53ef\u4ee5\u81ea\u5b9a\u4e49\u6765\u6e90\u9605\u8bfb\u7f51\u7edc\u5185\u5bb9\u7684\u5de5\u5177\uff0c\u4e3a\u5e7f\u5927\u7f51\u7edc\u6587\u5b66\u7231\u597d\u8005\u63d0\u4f9b\u4e00\u79cd\u65b9\u4fbf\u3001\u5feb\u6377\u8212\u9002\u7684\u8bd5\u8bfb\u4f53\u9a8c\u3002", "language": "Java", "repo": "MyBookshelf", "new_stars": 87, "stars": 3097, "owner": "gedoor", "forks": 849},
{"description": "Apache Dubbo is a high-performance, java based, open source RPC framework.", "language": "Java", "repo": "dubbo", "new_stars": 161, "stars": 28572, "owner": "apache", "forks": 18786},
{"description": "OpenAPI Generator allows generation of API client libraries (SDK generation), server stubs, documentation and configuration automatically given an OpenAPI Spec (v2, v3)", "language": "Java", "repo": "openapi-generator", "new_stars": 60, "stars": 2931, "owner": "OpenAPITools", "forks": 997},
{"description": "android 4.4\u4ee5\u4e0a\u6c89\u6d78\u5f0f\u72b6\u6001\u680f\u548c\u6c89\u6d78\u5f0f\u5bfc\u822a\u680f\u7ba1\u7406\uff0c\u9002\u914d\u6a2a\u7ad6\u5c4f\u5207\u6362\u3001\u5218\u6d77\u5c4f\u3001\u8f6f\u952e\u76d8\u5f39\u51fa\u7b49\u95ee\u9898\uff0c\u53ef\u4ee5\u4fee\u6539\u72b6\u6001\u680f\u5b57\u4f53\u989c\u8272\u548c\u5bfc\u822a\u680f\u56fe\u6807\u989c\u8272\uff0c\u4ee5\u53ca\u4e0d\u53ef\u4fee\u6539\u5b57\u4f53\u989c\u8272\u624b\u673a\u7684\u9002\u914d\uff0c\u9002\u7528\u4e8eActivity\u3001Fragment\u3001DialogFragment\u3001Dialog\uff0cPopupWindow\uff0c\u4e00\u53e5\u4ee3\u7801\u8f7b\u677e\u5b9e\u73b0\uff0c\u4ee5\u53ca\u5bf9bar\u7684\u5176\u4ed6\u8bbe\u7f6e\uff0c\u8be6\u89c1README\u3002\u7b80\u4e66\u8bf7\u53c2\u8003\uff1a", "language": "Java", "repo": "ImmersionBar", "new_stars": 59, "stars": 6753, "owner": "gyf-dev", "forks": 1133}
]