[
{"description": "Curated interview preparation materials for busy engineers", "language": "JavaScript", "repo": "tech-interview-handbook", "new_stars": 1357, "stars": 65028, "owner": "yangshun", "forks": 9031},
{"description": "The Cyber Swiss Army Knife - a web app for encryption, encoding, compression and data analysis", "language": "JavaScript", "repo": "CyberChef", "new_stars": 480, "stars": 15175, "owner": "gchq", "forks": 1913},
{"description": "Algorithms implemented in Javascript for beginners, following best practices.", "language": "JavaScript", "repo": "Javascript", "new_stars": 287, "stars": 16846, "owner": "TheAlgorithms", "forks": 2927},
{"description": "Budibase is an open-source low-code platform for creating internal apps in minutes. Supports PostgreSQL, MySQL, MSSQL, MongoDB, Rest API, Docker, K8s", "language": "JavaScript", "repo": "budibase", "new_stars": 196, "stars": 8702, "owner": "Budibase", "forks": 474},
{"description": "Desktop environment in the browser.", "language": "JavaScript", "repo": "daedalOS", "new_stars": 876, "stars": 3473, "owner": "DustinBrett", "forks": 170},
{"description": "Project Cider. A new look into listening and enjoying Apple Music in style and performance.", "language": "JavaScript", "repo": "Cider", "new_stars": 92, "stars": 382, "owner": "ciderapp", "forks": 46},
{"description": "Clean Code concepts adapted for JavaScript", "language": "JavaScript", "repo": "clean-code-javascript", "new_stars": 924, "stars": 63200, "owner": "ryanmcdermott", "forks": 8192},
{"description": "Versatile typeface for code, from code.", "language": "JavaScript", "repo": "Iosevka", "new_stars": 73, "stars": 13408, "owner": "be5invis", "forks": 437},
{"description": "A modern ebook manager and reader with sync and backup capacities for Windows, macOS, Linux and Web", "language": "JavaScript", "repo": "koodo-reader", "new_stars": 651, "stars": 3148, "owner": "troyeguo", "forks": 325},
{"description": "JavaScript 3D Library.", "language": "JavaScript", "repo": "three.js", "new_stars": 579, "stars": 78475, "owner": "mrdoob", "forks": 30406},
{"description": null, "language": "JavaScript", "repo": "Prep-Course", "new_stars": 21, "stars": 54, "owner": "soyHenry", "forks": 1404},
{"description": "List of 1000 JavaScript Interview Questions", "language": "JavaScript", "repo": "javascript-interview-questions", "new_stars": 186, "stars": 7695, "owner": "sudheerj", "forks": 2295},
{"description": "Google Chrome, Firefox, and Thunderbird extension that lets you write email in Markdown and render it before sending.", "language": "JavaScript", "repo": "markdown-here", "new_stars": 117, "stars": 54224, "owner": "adam-p", "forks": 10470},
{"description": "The React Framework", "language": "JavaScript", "repo": "next.js", "new_stars": 471, "stars": 80403, "owner": "vercel", "forks": 16457},
{"description": "A light-weight module that brings the Fetch API to Node.js", "language": "JavaScript", "repo": "node-fetch", "new_stars": 60, "stars": 7314, "owner": "node-fetch", "forks": 849},
{"description": "List of top 500 ReactJS Interview Questions & Answers....Coding exercise questions are coming soon!!", "language": "JavaScript", "repo": "reactjs-interview-questions", "new_stars": 171, "stars": 18561, "owner": "sudheerj", "forks": 4401},
{"description": "High performance and SEO friendly lazy loader for images (responsive and normal), iframes and more, that detects any visibility changes triggered through user interaction, CSS or JavaScript without configuration.", "language": "JavaScript", "repo": "lazysizes", "new_stars": 46, "stars": 15833, "owner": "aFarkas", "forks": 1669},
{"description": "A tool for managing JavaScript projects with multiple packages.", "language": "JavaScript", "repo": "lerna", "new_stars": 81, "stars": 31509, "owner": "lerna", "forks": 2067},
{"description": "A WhatsApp client library for NodeJS that connects through the WhatsApp Web browser app", "language": "JavaScript", "repo": "whatsapp-web.js", "new_stars": 158, "stars": 4466, "owner": "pedroslopez", "forks": 1105},
{"description": "UI-Lovelace-Minimalist is a \"theme\" for HomeAssistant", "language": "JavaScript", "repo": "UI", "new_stars": 38, "stars": 267, "owner": "UI-Lovelace-Minimalist", "forks": 71},
{"description": "33 JavaScript concepts every developer should know.", "language": "JavaScript", "repo": "33-js-concepts", "new_stars": 225, "stars": 46252, "owner": "leonardomso", "forks": 6175},
{"description": "The zero configuration build tool for the web.", "language": "JavaScript", "repo": "parcel", "new_stars": 114, "stars": 40069, "owner": "parcel-bundler", "forks": 2075},
{"description": "The Blooket Hack", "language": "JavaScript", "repo": "blooket-hack", "new_stars": 18, "stars": 370, "owner": "glixzzy", "forks": 1096},
{"description": "An open-source JavaScript library for world-class 3D globes and maps", "language": "JavaScript", "repo": "cesium", "new_stars": 31, "stars": 8230, "owner": "CesiumGS", "forks": 2743},
{"description": "The Block Editor project for WordPress and beyond. Plugin is available from the official repository.", "language": "JavaScript", "repo": "gutenberg", "new_stars": 29, "stars": 7477, "owner": "WordPress", "forks": 2730}
]