[
{"description": "30 Days of React challenge is a step by step guide to learn React in 30 days. It requires HTML, CSS, and JavaScript knowledge. You should be comfortable with JavaScript before you start to React. If you are not comfortable with JavaScript check out 30DaysOfJavaScript. This is a continuation of 30 Days Of JS. This challenge may take more than 100\u2026", "language": "JavaScript", "repo": "30-Days-Of-React", "new_stars": 1506, "stars": 12881, "owner": "Asabeneh", "forks": 3278},
{"description": "30 days of JavaScript programming challenge is a step-by-step guide to learn JavaScript programming language in 30 days. This challenge may take more than 100 days, please just follow your own pace.", "language": "JavaScript", "repo": "30-Days-Of-JavaScript", "new_stars": 666, "stars": 22274, "owner": "Asabeneh", "forks": 4776},
{"description": "The most popular HTML, CSS, and JavaScript framework for developing responsive, mobile first projects on the web.", "language": "JavaScript", "repo": "bootstrap", "new_stars": 235, "stars": 157754, "owner": "twbs", "forks": 76758},
{"description": "A declarative, efficient, and flexible JavaScript library for building user interfaces.", "language": "JavaScript", "repo": "react", "new_stars": 488, "stars": 189040, "owner": "facebook", "forks": 38979},
{"description": "\u55b5\u5e01\u52a9\u624b\uff1a618\u5929\u732b\uff08\u6dd8\u5b9d\uff09\u3001\u4eac\u4e1c\u4efb\u52a1\u4e00\u952e\u5b8c\u6210\u3002\u57fa\u4e8eAuto.JS\u3002", "language": "JavaScript", "repo": "tmall-miao", "new_stars": 251, "stars": 2123, "owner": "MonsterNone", "forks": 339},
{"description": null, "language": "JavaScript", "repo": "tasks", "new_stars": 153, "stars": 1901, "owner": "rolling-scopes-school", "forks": 3789},
{"description": "The Full-Stack Web Framework for Go", "language": "JavaScript", "repo": "bud", "new_stars": 1199, "stars": 3038, "owner": "livebud", "forks": 89},
{"description": "Algorithms and data structures implemented in JavaScript with explanations and links to further readings", "language": "JavaScript", "repo": "javascript-algorithms", "new_stars": 947, "stars": 142988, "owner": "trekhleb", "forks": 23616},
{"description": "This is a code repository for the corresponding YouTube video. In this tutorial we are going to build and deploy a an admin dashboard app using React.js and Syncfusion", "language": "JavaScript", "repo": "project_syncfusion_dashboard", "new_stars": 152, "stars": 748, "owner": "adrianhajdin", "forks": 193},
{"description": "Clean Code concepts adapted for JavaScript", "language": "JavaScript", "repo": "clean-code-javascript", "new_stars": 315, "stars": 68352, "owner": "ryanmcdermott", "forks": 9111},
{"description": "Curated interview preparation materials for busy engineers", "language": "JavaScript", "repo": "tech-interview-handbook", "new_stars": 633, "stars": 71353, "owner": "yangshun", "forks": 9786},
{"description": "The React Framework", "language": "JavaScript", "repo": "next.js", "new_stars": 381, "stars": 87606, "owner": "vercel", "forks": 18633},
{"description": "The Block Editor project for WordPress and beyond. Plugin is available from the official repository.", "language": "JavaScript", "repo": "gutenberg", "new_stars": 92, "stars": 7901, "owner": "WordPress", "forks": 2985},
{"description": "AdminLTE - Free admin dashboard template based on Bootstrap 4", "language": "JavaScript", "repo": "AdminLTE", "new_stars": 63, "stars": 41023, "owner": "ColorlibHQ", "forks": 17670},
{"description": "The communications platform that puts data protection first.", "language": "JavaScript", "repo": "Rocket.Chat", "new_stars": 76, "stars": 32435, "owner": "RocketChat", "forks": 7440},
{"description": "Fast, easy and reliable testing for anything that runs in a browser.", "language": "JavaScript", "repo": "cypress", "new_stars": 138, "stars": 38711, "owner": "cypress-io", "forks": 2367},
{"description": "List of 1000 JavaScript Interview Questions", "language": "JavaScript", "repo": "javascript-interview-questions", "new_stars": 178, "stars": 10168, "owner": "sudheerj", "forks": 2976},
{"description": "Odoo. Open Source Apps To Grow Your Business.", "language": "JavaScript", "repo": "odoo", "new_stars": 82, "stars": 25195, "owner": "odoo", "forks": 16305},
{"description": "Ace (Ajax.org Cloud9 Editor)", "language": "JavaScript", "repo": "ace", "new_stars": 32, "stars": 24469, "owner": "ajaxorg", "forks": 5174},
{"description": "Possibly the smallest compiler ever", "language": "JavaScript", "repo": "the-super-tiny-compiler", "new_stars": 110, "stars": 22688, "owner": "jamiebuilds", "forks": 2502},
{"description": "GO implementation of the Terra 2.0 Protocol", "language": "JavaScript", "repo": "core", "new_stars": 22, "stars": 276, "owner": "terra-money", "forks": 38},
{"description": "Bring data to life with SVG, Canvas and HTML.", "language": "JavaScript", "repo": "d3", "new_stars": 94, "stars": 101440, "owner": "d3", "forks": 23109},
{"description": "Connect APIs, remarkably fast. Free for developers.", "language": "JavaScript", "repo": "pipedream", "new_stars": 94, "stars": 3423, "owner": "PipedreamHQ", "forks": 2009},
{"description": "\u6df1\u5ea6\u5b66\u4e60500\u95ee\uff0c\u4ee5\u95ee\u7b54\u5f62\u5f0f\u5bf9\u5e38\u7528\u7684\u6982\u7387\u77e5\u8bc6\u3001\u7ebf\u6027\u4ee3\u6570\u3001\u673a\u5668\u5b66\u4e60\u3001\u6df1\u5ea6\u5b66\u4e60\u3001\u8ba1\u7b97\u673a\u89c6\u89c9\u7b49\u70ed\u70b9\u95ee\u9898\u8fdb\u884c\u9610\u8ff0\uff0c\u4ee5\u5e2e\u52a9\u81ea\u5df1\u53ca\u6709\u9700\u8981\u7684\u8bfb\u8005\u3002 \u5168\u4e66\u5206\u4e3a18\u4e2a\u7ae0\u8282\uff0c50\u4f59\u4e07\u5b57\u3002\u7531\u4e8e\u6c34\u5e73\u6709\u9650\uff0c\u4e66\u4e2d\u4e0d\u59a5\u4e4b\u5904\u6073\u8bf7\u5e7f\u5927\u8bfb\u8005\u6279\u8bc4\u6307\u6b63\u3002 \u672a\u5b8c\u5f85\u7eed............ \u5982\u6709\u610f\u5408\u4f5c\uff0c\u8054\u7cfbscutjy2015@163.com \u7248\u6743\u6240\u6709\uff0c\u8fdd\u6743\u5fc5\u7a76 Tan 2018.06", "language": "JavaScript", "repo": "DeepLearning-500-questions", "new_stars": 116, "stars": 48137, "owner": "scutan90", "forks": 15094},
{"description": "Awesome cheatsheets for popular programming languages, frameworks and development tools. They include everything you should know in one single file.", "language": "JavaScript", "repo": "awesome-cheatsheets", "new_stars": 142, "stars": 28835, "owner": "LeCoupa", "forks": 4679}
]