[
{"description": "Starter files, final projects and FAQ for my Complete JavaScript course", "language": "JavaScript", "repo": "complete-javascript-course", "new_stars": 117, "stars": 4893, "owner": "jonasschmedtmann", "forks": 6517},
{"description": "A Chrome extension that demonstrates bypassing Widevine L3 DRM", "language": "JavaScript", "repo": "widevine-l3-decryptor", "new_stars": 134, "stars": 372, "owner": "tomer8007", "forks": 54},
{"description": "A UiAutomator on android, does not need root access(\u5b89\u5353\u5e73\u53f0\u4e0a\u7684JavaScript\u81ea\u52a8\u5316\u5de5\u5177)", "language": "Java", "repo": "Auto.js", "new_stars": 95, "stars": 7848, "owner": "hyb1996", "forks": 2210},
{"description": "Facebook AI Research Sequence-to-Sequence Toolkit written in Python.", "language": "Python", "repo": "fairseq", "new_stars": 140, "stars": 9774, "owner": "pytorch", "forks": 2448},
{"description": "Node.js JavaScript runtime", "language": "JavaScript", "repo": "node", "new_stars": 87, "stars": 73960, "owner": "nodejs", "forks": 18296},
{"description": "\u4eac\u4e1c\u8585\u7f8a\u6bdb\u5de5\u5177, \u4eac\u4e1c\u6c34\u679c\u3001\u5ba0\u7269\u3001\u79cd\u8c46 aff \u4e92\u52a9\u8ba8\u8bba\u7ec4\uff1a", "language": "JavaScript", "repo": "scripts", "new_stars": 70, "stars": 981, "owner": "lxk0301", "forks": 1032},
{"description": "A declarative, efficient, and flexible JavaScript library for building user interfaces.", "language": "JavaScript", "repo": "react", "new_stars": 125, "stars": 157826, "owner": "facebook", "forks": 31216},
{"description": "\u5f00\u653e\u5f0f\u8de8\u7aef\u8de8\u6846\u67b6\u89e3\u51b3\u65b9\u6848\uff0c\u652f\u6301\u4f7f\u7528 React/Vue/Nerv \u7b49\u6846\u67b6\u6765\u5f00\u53d1\u5fae\u4fe1/\u4eac\u4e1c/\u767e\u5ea6/\u652f\u4ed8\u5b9d/\u5b57\u8282\u8df3\u52a8/ QQ \u5c0f\u7a0b\u5e8f/H5 \u7b49\u5e94\u7528\u3002", "language": "JavaScript", "repo": "taro", "new_stars": 34, "stars": 27242, "owner": "NervJS", "forks": 3368},
{"description": "CLI tool for Angular", "language": "TypeScript", "repo": "angular-cli", "new_stars": 24, "stars": 23900, "owner": "angular", "forks": 9798},
{"description": "nginx Docker image secure by default.", "language": "Shell", "repo": "bunkerized-nginx", "new_stars": 278, "stars": 1316, "owner": "bunkerity", "forks": 47},
{"description": "\u5bf9\u5f00\u53d1\u4eba\u5458\u6709\u7528\u7684\u5b9a\u5f8b\u3001\u7406\u8bba\u3001\u539f\u5219\u548c\u6a21\u5f0f\u3002(Laws, Theories, Principles and Patterns that developers will find useful.)", "language": null, "repo": "hacker-laws-zh", "new_stars": 209, "stars": 6769, "owner": "nusr", "forks": 590},
{"description": null, "language": null, "repo": "JAVA-000", "new_stars": 6, "stars": 70, "owner": "JAVA-000", "forks": 804},
{"description": "A powerful JavaScript library for interacting with the Discord API", "language": "JavaScript", "repo": "discord.js", "new_stars": 121, "stars": 7756, "owner": "discordjs", "forks": 1733},
{"description": "Microsoft Azure PowerShell", "language": "C#", "repo": "azure-powershell", "new_stars": 31, "stars": 2281, "owner": "Azure", "forks": 2271},
{"description": "Practical Python Programming (course by", "language": "Python", "repo": "practical-python", "new_stars": 150, "stars": 6478, "owner": "dabeaz-course", "forks": 2872},
{"description": "A GUI for Pandas DataFrames", "language": "Python", "repo": "pandasgui", "new_stars": 149, "stars": 977, "owner": "adamerose", "forks": 51},
{"description": "\"The mother of all demo apps\" \u2014 Exemplary fullstack Medium.com clone powered by React, Angular, Node, Django, and many more", "language": "JavaScript", "repo": "realworld", "new_stars": 221, "stars": 48867, "owner": "gothinkster", "forks": 4139},
{"description": "The fastest JSON library in C", "language": "C", "repo": "yyjson", "new_stars": 237, "stars": 705, "owner": "ibireme", "forks": 27},
{"description": "A cross-platform, customizable science fiction terminal emulator with advanced monitoring & touchscreen support.", "language": "JavaScript", "repo": "edex-ui", "new_stars": 348, "stars": 17401, "owner": "GitSquared", "forks": 1028},
{"description": "A Kubernetes Resource Interface for the Edge", "language": "Rust", "repo": "akri", "new_stars": 70, "stars": 202, "owner": "deislabs", "forks": 16},
{"description": "What the f*ck Python?", "language": "Python", "repo": "wtfpython", "new_stars": 210, "stars": 22108, "owner": "satwikkansal", "forks": 2003},
{"description": "Cybernetically enhanced web apps", "language": "JavaScript", "repo": "svelte", "new_stars": 340, "stars": 38447, "owner": "sveltejs", "forks": 1832},
{"description": "The fastai book, published as Jupyter Notebooks", "language": "Jupyter Notebook", "repo": "fastbook", "new_stars": 73, "stars": 9884, "owner": "fastai", "forks": 2793},
{"description": "A professional front-end template for building fast, robust, and adaptable web apps or sites.", "language": "JavaScript", "repo": "html5-boilerplate", "new_stars": 161, "stars": 47544, "owner": "h5bp", "forks": 11142},
{"description": "Leak git repositories from misconfigured websites", "language": "Go", "repo": "gitjacker", "new_stars": 227, "stars": 914, "owner": "liamg", "forks": 62}
]